extra/__init__.py
extra/iota.py
extra_hv01-1.0.0.dist-info/METADATA
extra_hv01-1.0.0.dist-info/WHEEL
extra_hv01-1.0.0.dist-info/top_level.txt
extra_hv01-1.0.0.dist-info/RECORD
