Metadata-Version: 2.1
Name: extra-hv01
Version: 1.0.0
Summary: A sample packages with hierarchical modules
Author: Harold Vasquez
